pantsbuild.pants.contrib.android-1.6.0-py2.7-nspkg.pth
pants/contrib/android/android_config_util.py
pants/contrib/android/android_manifest_parser.py
pants/contrib/android/register.py
pants/contrib/android/distribution/android_distribution.py
pants/contrib/android/keystore/keystore_resolver.py
pants/contrib/android/targets/android_binary.py
pants/contrib/android/targets/android_dependency.py
pants/contrib/android/targets/android_library.py
pants/contrib/android/targets/android_resources.py
pants/contrib/android/targets/android_target.py
pants/contrib/android/tasks/aapt_builder.py
pants/contrib/android/tasks/aapt_gen.py
pants/contrib/android/tasks/aapt_task.py
pants/contrib/android/tasks/android_task.py
pants/contrib/android/tasks/dx_compile.py
pants/contrib/android/tasks/sign_apk.py
pants/contrib/android/tasks/unpack_libraries.py
pants/contrib/android/tasks/zipalign.py
pantsbuild.pants.contrib.android-1.6.0.dist-info/DESCRIPTION.rst
pantsbuild.pants.contrib.android-1.6.0.dist-info/METADATA
pantsbuild.pants.contrib.android-1.6.0.dist-info/RECORD
pantsbuild.pants.contrib.android-1.6.0.dist-info/WHEEL
pantsbuild.pants.contrib.android-1.6.0.dist-info/entry_points.txt
pantsbuild.pants.contrib.android-1.6.0.dist-info/metadata.json
pantsbuild.pants.contrib.android-1.6.0.dist-info/namespace_packages.txt
pantsbuild.pants.contrib.android-1.6.0.dist-info/top_level.txt
pantsbuild.pants.contrib.android-1.6.0.dist-info/zip-safe
