Metadata-Version: 2.0
Name: pantsbuild.pants.contrib.android
Version: 1.6.0
Summary: Android Pants plugin
Home-page: https://github.com/pantsbuild/pants
Author: UNKNOWN
Author-email: UNKNOWN
License: Apache License, Version 2.0
Platform: UNKNOWN
Classifier: Intended Audience :: Developers
Classifier: License :: OSI Approved :: Apache Software License
Classifier: Operating System :: MacOS :: MacOS X
Classifier: Operating System :: POSIX :: Linux
Classifier: Programming Language :: Python
Classifier: Topic :: Software Development :: Build Tools
Classifier: Topic :: Software Development :: Code Generators
Requires-Dist: pantsbuild.pants (==1.6.0)
Requires-Dist: twitter.common.collections (<0.4,>=0.3.1)
